{
  "products": [
    {
      "img": [
        "string",
        "string"
      ],
      "name": "string1",
      "desc": "string",
      "price": 55,
      "rate": {
        "rate": 4.2,
        "count": 7
      },
      "category": {
        "category": "kit",
        "name": "Наборы"
      }
    },
    {
      "img": [
        "string",
        "string"
      ],
      "name": "string2",
      "desc": "string",
      "price": 55,
      "rate": {
        "rate": 4.2,
        "count": 7
      },
      "category": {
        "category": "kit",
        "name": "Наборы"
      }
    },
    {
      "img": [
        "string",
        "string"
      ],
      "name": "string3",
      "desc": "string",
      "price": 55,
      "rate": {
        "rate": 4.2,
        "count": 7
      },
      "category": {
        "category": "kit",
        "name": "Наборы"
      }
    },
    {
      "img": [
        "string",
        "string"
      ],
      "name": "string4",
      "desc": "string",
      "price": 55,
      "rate": {
        "rate": 4.2,
        "count": 7
      },
      "category": {
        "category": "kit",
        "name": "Наборы"
      }
    },
    {
      "img": [
        "string",
        "string"
      ],
      "name": "string5",
      "desc": "string",
      "price": 55,
      "rate": {
        "rate": 4.2,
        "count": 7
      },
      "category": {
        "category": "kit",
        "name": "Наборы"
      }
    },
    {
      "img": [
        "string",
        "string"
      ],
      "name": "string6",
      "desc": "string",
      "price": 55,
      "rate": {
        "rate": 4.2,
        "count": 7
      },
      "category": {
        "category": "masks",
        "name": "Маски"
      }
    }
  ],
  "users": [
    {
      "id": 1,
      "name": "Илья",
      "surname": "Слипец",
      "patronymic": "КакЕгоТамович",
      "phone": 79780001122,
      "email": "ilya123558ilya@gmail.com"
    },
    {
      "id": 2,
      "name": "Неилья",
      "surname": "Неслипец",
      "patronymic": "КакЕгоТамович",
      "phone": 79780001122,
      "email": "ilya123558ilya@gmail.com"
    },
    {
      "id": 3,
      "name": "Хтоя",
      "surname": "Слипец",
      "patronymic": "КакЕгоТамович",
      "phone": 79780001122,
      "email": "ilya123558ilya@gmail.com"
    },
    {
      "name": "Ivan",
      "surname": "Ivanov",
      "patronymic": "Ivanovich",
      "phone": 7999999999,
      "email": "ilya123558ilya@gmail.com",
      "id": 4
    }
  ]
}